setup.py
meteorpi_client/__init__.py
meteorpi_client.egg-info/PKG-INFO
meteorpi_client.egg-info/SOURCES.txt
meteorpi_client.egg-info/dependency_links.txt
meteorpi_client.egg-info/not-zip-safe
meteorpi_client.egg-info/requires.txt
meteorpi_client.egg-info/top_level.txt