Metadata-Version: 1.1
Name: meteorpi-client
Version: 0.1.5
Summary: Client to the MeteorPi HTTP API
Home-page: https://github.com/camsci/meteor-pi/
Author: Tom Oinn
Author-email: tomoinn@crypticsquid.com
License: GPL
Platform: UNKNOWN
Classifier: Programming Language :: Python :: 2.7
